Credito_SQLViaCode/SQLViaCode.py
Credito_SQLViaCode/__init__.py
Credito_SQLViaCode-0.2.1.dist-info/METADATA
Credito_SQLViaCode-0.2.1.dist-info/WHEEL
Credito_SQLViaCode-0.2.1.dist-info/top_level.txt
Credito_SQLViaCode-0.2.1.dist-info/RECORD
