Metadata-Version: 2.1
Name: Credito-SQLViaCode
Version: 0.2.1
Summary: A Python package to execute SQL queries and procedures and manage backups.
Author: Afik Ratzon
Author-email: afik.ratzon@gmail.com
Classifier: Programming Language :: Python :: 3
Classifier: License :: OSI Approved :: MIT License
Classifier: Operating System :: OS Independent
Requires-Python: >=3.6
Requires-Dist: backports.tarfile ==1.2.0
Requires-Dist: certifi ==2024.8.30
Requires-Dist: charset-normalizer ==3.4.0
Requires-Dist: docutils ==0.21.2
Requires-Dist: greenlet ==3.1.1
Requires-Dist: idna ==3.10
Requires-Dist: importlib-metadata ==8.5.0
Requires-Dist: jaraco.classes ==3.4.0
Requires-Dist: jaraco.context ==6.0.1
Requires-Dist: jaraco.functools ==4.1.0
Requires-Dist: keyring ==25.5.0
Requires-Dist: markdown-it-py ==3.0.0
Requires-Dist: mdurl ==0.1.2
Requires-Dist: more-itertools ==10.5.0
Requires-Dist: nh3 ==0.2.19
Requires-Dist: numpy ==2.1.3
Requires-Dist: packaging ==24.2
Requires-Dist: pandas ==2.2.3
Requires-Dist: pkginfo ==1.11.2
Requires-Dist: Pygments ==2.18.0
Requires-Dist: pyodbc ==5.2.0
Requires-Dist: python-dateutil ==2.9.0.post0
Requires-Dist: python-dotenv ==1.0.1
Requires-Dist: pytz ==2024.2
Requires-Dist: pywin32-ctypes ==0.2.3
Requires-Dist: readme-renderer ==44.0
Requires-Dist: requests ==2.32.3
Requires-Dist: requests-toolbelt ==1.0.0
Requires-Dist: rfc3986 ==2.0.0
Requires-Dist: rich ==13.9.4
Requires-Dist: six ==1.16.0
Requires-Dist: SQLAlchemy ==2.0.36
Requires-Dist: tabulate ==0.9.0
Requires-Dist: twine ==6.0.1
Requires-Dist: typing-extensions ==4.12.2
Requires-Dist: tzdata ==2024.2
Requires-Dist: urllib3 ==2.2.3
Requires-Dist: zipp ==3.21.0
